<llsd>
    <map>
    <key>ambient</key>
        <array>
            <real>0.3353118896484375</real>
            <real>0.2506256103515625</real>
            <real>0.2744437158107757568359375</real>
            <real>0.1117706298828125</real>
        </array>
    <key>blue_density</key>
        <array>
            <real>0.446580827236175537109375</real>
            <real>0.47430419921875</real>
            <real>0.11944580078125</real>
            <real>0.237152099609375</real>
        </array>
    <key>blue_horizon</key>
        <array>
            <real>0.471038818359375</real>
            <real>0.294586181640625</real>
            <real>0.294586241245269775390625</real>
            <real>0.2355194091796875</real>
        </array>
    <key>cloud_color</key>
        <array>
            <real>0.2261539995670318603515625</real>
            <real>0.2261539995670318603515625</real>
            <real>0.2261539995670318603515625</real>
            <real>1</real>
        </array>
    <key>cloud_pos_density1</key>
        <array>
            <real>1.20466005802154541015625</real>
            <real>0.515474975109100341796875</real>
            <real>1</real>
            <real>1</real>
        </array>
    <key>cloud_pos_density2</key>
        <array>
            <real>1.20466005802154541015625</real>
            <real>0.515474975109100341796875</real>
            <real>0.125</real>
            <real>1</real>
        </array>
    <key>cloud_scale</key>
        <array>
            <real>0.4199999868869781494140625</real>
            <real>0</real>
            <real>0</real>
            <real>1</real>
        </array>
    <key>cloud_scroll_rate</key>
        <array>
            <real>10.49940013885498046875</real>
            <real>10.0109996795654296875</real>
        </array>
    <key>cloud_shadow</key>
        <array>
            <real>0.33064401149749755859375</real>
            <real>0</real>
            <real>0</real>
            <real>1</real>
        </array>
    <key>density_multiplier</key>
        <array>
            <real>0.0003100000030826777219772339</real>
            <real>0</real>
            <real>0</real>
            <real>1</real>
        </array>
    <key>distance_multiplier</key>
        <array>
            <real>10.30000019073486328125</real>
            <real>0</real>
            <real>0</real>
            <real>1</real>
        </array>
    <key>east_angle</key>
        <real>0.942477762699127197265625</real>
    <key>enable_cloud_scroll</key>
        <array>
            <boolean>1</boolean>
            <boolean>1</boolean>
        </array>
    <key>gamma</key>
        <array>
            <real>1.5</real>
            <real>0</real>
            <real>0</real>
            <real>1</real>
        </array>
    <key>glow</key>
        <array>
            <real>39.979999542236328125</real>
            <real>0.001000000047497451305389404</real>
            <real>-0.85000002384185791015625</real>
            <real>1</real>
        </array>
    <key>haze_density</key>
        <array>
            <real>1.5880000591278076171875</real>
            <real>0</real>
            <real>0</real>
            <real>1</real>
        </array>
    <key>haze_horizon</key>
        <array>
            <real>0.57400000095367431640625</real>
            <real>0.1991560012102127075195313</real>
            <real>0.1991560012102127075195313</real>
            <real>1</real>
        </array>
    <key>lightnorm</key>
        <array>
            <real>-0.796726286411285400390625</real>
            <real>0.17364752292633056640625</real>
            <real>0.578855574131011962890625</real>
            <real>0</real>
        </array>
    <key>max_y</key>
        <array>
            <real>618</real>
            <real>0</real>
            <real>0</real>
            <real>1</real>
        </array>
    <key>preset_num</key>
        <integer>27</integer>
    <key>star_brightness</key>
        <real>0</real>
    <key>sun_angle</key>
        <real>0.1745322644710540771484375</real>
    <key>sunlight_color</key>
        <array>
            <real>2.81011962890625</real>
            <real>1.31847667694091796875</real>
            <real>0.33050537109375</real>
            <real>0.93670654296875</real>
        </array>
    </map>
</llsd>
